dict_recursive_update/__init__.py
dict_recursive_update-1.0.0.dist-info/DESCRIPTION.rst
dict_recursive_update-1.0.0.dist-info/METADATA
dict_recursive_update-1.0.0.dist-info/RECORD
dict_recursive_update-1.0.0.dist-info/WHEEL
dict_recursive_update-1.0.0.dist-info/metadata.json
dict_recursive_update-1.0.0.dist-info/top_level.txt
