Metadata-Version: 2.0
Name: dict-recursive-update
Version: 1.0.0
Summary: A Python module who does recursive update work on 2 dicts.
Home-page: https://github.com/Maples7/dict-recursive-update
Author: Maples7
Author-email: maples7@163.com
License: MIT
Keywords: dict recursive update
Platform: UNKNOWN
Classifier: Development Status :: 5 - Production/Stable
Classifier: Intended Audience :: Developers
Classifier: Topic :: Software Development :: Libraries :: Python Modules
Classifier: License :: OSI Approved :: MIT License
Classifier: Programming Language :: Python :: 2.6
Classifier: Programming Language :: Python :: 2.7
Classifier: Programming Language :: Python :: 3.3
Classifier: Programming Language :: Python :: 3.4
Classifier: Programming Language :: Python :: 3.5
Classifier: Programming Language :: Python :: 3.6
